programmingexcuses/__init__.py
programmingexcuses/programmingexcuses.py
programmingexcuses-0.1.3.data/scripts/programmingexcuse
programmingexcuses-0.1.3.dist-info/METADATA
programmingexcuses-0.1.3.dist-info/WHEEL
programmingexcuses-0.1.3.dist-info/top_level.txt
programmingexcuses-0.1.3.dist-info/RECORD
