Metadata-Version: 2.1
Name: programmingexcuses
Version: 0.1.3
Summary: Tired of making up your own excuses?
Home-page: https://github.com/crossnox/programmingexcuses
Author: CrossNox
Author-email: UNKNOWN
License: UNKNOWN
Platform: UNKNOWN
Classifier: Programming Language :: Python :: 2
Classifier: Programming Language :: Python :: 3
Requires-Dist: requests
Requires-Dist: bs4
